pytimeparse/__init__.py
pytimeparse/timeparse.py
pytimeparse/VERSION
pytimeparse/tests/__init__.py
pytimeparse/tests/testtimeparse.py
pytimeparse-1.1.7.dist-info/DESCRIPTION.rst
pytimeparse-1.1.7.dist-info/METADATA
pytimeparse-1.1.7.dist-info/metadata.json
pytimeparse-1.1.7.dist-info/RECORD
pytimeparse-1.1.7.dist-info/top_level.txt
pytimeparse-1.1.7.dist-info/WHEEL
