Metadata-Version: 1.1
Name: pytimeparse
Version: 1.1.7
Summary: Time expression parser
Home-page: https://github.com/wroberts/pytimeparse
Author: Will Roberts
Author-email: wildwilhelm@gmail.com
License: License :: OSI Approved :: MIT License
Keywords: time parsing parser
Platform: UNKNOWN
Classifier: Development Status :: 4 - Beta
Classifier: Intended Audience :: Developers
Classifier: Topic :: Text Processing
Classifier: Natural Language :: English
Classifier: License :: OSI Approved :: MIT License
Classifier: Programming Language :: Python :: 2
Classifier: Programming Language :: Python :: 2.7
Classifier: Programming Language :: Python :: 3
Classifier: Programming Language :: Python :: 3.2
Classifier: Programming Language :: Python :: 3.3
Classifier: Programming Language :: Python :: 3.4
Classifier: Programming Language :: Python :: 3.5
Classifier: Programming Language :: Python :: 3.6
